datastructures/App.py
datastructures/Linear/LLQueue.py
datastructures/Linear/LLStack.py
datastructures/Linear/doublyCLL.py
datastructures/Linear/doublyLL.py
datastructures/Linear/singlyCLL.py
datastructures/Linear/singlyLL.py
datastructures/nodes/DNode.py
datastructures/nodes/SNode.py
datastructures/nodes/TNode.py
datastructures/treestructures/AVL.py
datastructures/treestructures/BST.py
DatastructuresENSF338_Alex_Kaylyn-1.0.dist-info/METADATA
DatastructuresENSF338_Alex_Kaylyn-1.0.dist-info/WHEEL
DatastructuresENSF338_Alex_Kaylyn-1.0.dist-info/top_level.txt
DatastructuresENSF338_Alex_Kaylyn-1.0.dist-info/RECORD
